vmush/__init__.py
vmush/conf.py
vmush/config.py
vmush/conn.py
vmush/launcher.py
vmush/models.py
vmush/selectscreen.py
vmush/welcome.py
vmush-0.0.1.data/scripts/vmush
vmush-0.0.1.dist-info/METADATA
vmush-0.0.1.dist-info/WHEEL
vmush-0.0.1.dist-info/top_level.txt
vmush-0.0.1.dist-info/RECORD
