Metadata-Version: 2.1
Name: vmush
Version: 0.0.1
Summary: UNKNOWN
Home-page: https://github.com/volundmush/vmush
Author: Volund
Maintainer: Volund
License: ???
Project-URL: Source, https://github.com/volundmush/vmush
Project-URL: Issue tracker, https://github.com/volundmush/vmush/issues
Project-URL: Patreon, https://www.patreon.com/volund
Platform: UNKNOWN
Requires-Python: >=3.7
Requires-Dist: pymush
Requires-Dist: django (>=3.2)
